odoo/addons/donation_bank_statement/README.rst
odoo/addons/donation_bank_statement/__init__.py
odoo/addons/donation_bank_statement/__manifest__.py
odoo/addons/donation_bank_statement/demo/demo.xml
odoo/addons/donation_bank_statement/i18n/de.po
odoo/addons/donation_bank_statement/i18n/donation_bank_statement.pot
odoo/addons/donation_bank_statement/i18n/fr.po
odoo/addons/donation_bank_statement/models/__init__.py
odoo/addons/donation_bank_statement/models/account_config_settings.py
odoo/addons/donation_bank_statement/models/bank_statement.py
odoo/addons/donation_bank_statement/models/company.py
odoo/addons/donation_bank_statement/models/donation.py
odoo/addons/donation_bank_statement/models/res_config_settings.py
odoo/addons/donation_bank_statement/readme/CONFIGURE.rst
odoo/addons/donation_bank_statement/readme/CONTRIBUTORS.rst
odoo/addons/donation_bank_statement/readme/DESCRIPTION.rst
odoo/addons/donation_bank_statement/readme/USAGE.rst
odoo/addons/donation_bank_statement/security/ir.model.access.csv
odoo/addons/donation_bank_statement/static/description/icon.png
odoo/addons/donation_bank_statement/static/description/index.html
odoo/addons/donation_bank_statement/tests/__init__.py
odoo/addons/donation_bank_statement/tests/test_bank_statement.py
odoo/addons/donation_bank_statement/tests/test_company.py
odoo/addons/donation_bank_statement/tests/test_donation.py
odoo/addons/donation_bank_statement/views/bank_statement.xml
odoo/addons/donation_bank_statement/views/donation.xml
odoo/addons/donation_bank_statement/views/res_config_settings.xml
odoo11_addon_donation_bank_statement-11.0.1.0.0.99.dev4.dist-info/METADATA
odoo11_addon_donation_bank_statement-11.0.1.0.0.99.dev4.dist-info/WHEEL
odoo11_addon_donation_bank_statement-11.0.1.0.0.99.dev4.dist-info/top_level.txt
odoo11_addon_donation_bank_statement-11.0.1.0.0.99.dev4.dist-info/RECORD
